{
    "version": "20200620",
    "description": "Query the timetable of China Railway passenger transport.",
    "homepage": "http://www.lltskb.com/",
    "license": "Freeware",
    "url": "http://down.lltskb.com/lltskb.rar",
    "hash": "793c5e9935a2144987700289bf9441a1a4b97a030b34a58065aefe3ee94343d4",
    "shortcuts": [
        [
            "lltskb.exe",
            "路路通"
        ]
    ],
    "checkver": {
        "url": "http://lltskb.com/view/32.html",
        "regex": "路路通软件pc电脑版    ([\\d.]+)"
    },
    "autoupdate": {
        "url": "http://down.lltskb.com/lltskb.rar"
    }
}
