{
    "version": "20210415",
    "description": "Query the timetable of China Railway passenger transport.",
    "homepage": "http://www.lltskb.com/",
    "license": "Freeware",
    "url": "http://down.lltskb.com/lltskb.rar",
    "hash": "d48202fbd57ba50aee9259a32131389e06e4760f946a62f0a7e9d2c051c0f01d",
    "shortcuts": [
        [
            "lltskb.exe",
            "路路通"
        ]
    ],
    "checkver": {
        "url": "http://lltskb.com/view/32.html",
        "regex": "(\\d{8})"
    },
    "autoupdate": {
        "url": "http://down.lltskb.com/lltskb.rar"
    }
}
