{
    "version": "8.2.2.6",
    "description": "Manage your Microsoft Office install.",
    "homepage": "https://otp.landian.vip/",
    "license": "Proprietary",
    "url": "https://github.com/YerongAI/Office-Tool/releases/download/8.2.2.6/Office-Tool-v8.2.zip",
    "hash": "22abbe4c28b3e111069644e6a40350f6122c2911a75c12c2d05bd037325e6fef",
    "extract_dir": "Office Tool",
    "shortcuts": [
        [
            "Office Tool Plus.exe",
            "Office Tool Plus"
        ]
    ],
    "persist": [
        "files",
        "Office"
    ],
    "checkver": {
        "github": "https://github.com/YerongAI/Office-Tool"
    },
    "autoupdate": {
        "url": "https://github.com/YerongAI/Office-Tool/releases/download/$version/Office-Tool-v$majorVersion.$minorVersion.zip",
        "hash": {
            "url": "https://github.com/YerongAI/Office-Tool/releases/latest",
            "regex": "Office_Tool_v[\\d.]+\\.zip</td>\\n<td [a-z\"=]+>([a-fA-F0-9]{64})"
        }
    }
}
